Metadata-Version: 2.1
Name: os-xcode-tools
Version: 1.21
Summary: a bunch of tools for python xcode project development 
Home-page: https://github.com/osfunapps/os-xcode-tools-py
Author: Oz Shabat
Author-email: admin@os-apps.com
License: MIT
Keywords: python,osfunapps,files,xcode,apple,ios,tools,utils
Platform: UNKNOWN
Classifier: Development Status :: 5 - Production/Stable
Classifier: Intended Audience :: Developers
Classifier: Topic :: Software Development :: Build Tools
Classifier: License :: OSI Approved :: MIT License
Classifier: Programming Language :: Python :: 3
Classifier: Programming Language :: Python :: 3.4
Classifier: Programming Language :: Python :: 3.5
Classifier: Programming Language :: Python :: 3.6
Classifier: Programming Language :: Python :: 3.9
License-File: LICENSE.txt
